{
    "name": "System | CPU Queue Length | Too High",
    "$collection": "fm.eventclasses",
    "uuid": "f4844d01-2370-43be-88d3-c22902775c4f",
    "description": "CPU Queue Length Threshold class",
    "action": "L",
    "vars": [
        {
            "name": "cpu_id",
            "description": "CPU Identifier (CPU Slot)",
            "type": "str",
            "required": false,
            "match_suppress": false
        },
        {
            "name": "tvalue",
            "description": "Threshold Value",
            "type": "float",
            "required": true,
            "match_suppress": false
        },
        {
            "name": "ovalue",
            "description": "Utilization Value",
            "type": "float",
            "required": false,
            "match_suppress": false
        },
        {
            "name": "tstate",
            "description": "Threshold State: error, critical",
            "type": "str",
            "required": false,
            "match_suppress": false
        },
        {
            "name": "window_size",
            "description": "Window size for calculate value",
            "type": "int",
            "required": false,
            "match_suppress": false
        }
    ],
    "deduplication_window": 3,
    "suppression_window": 0,
    "ttl": 86400,
    "subject_template": "CPU Queue Length {{ ovalue }}% {% if tvalue %} overload threshold {{ tvalue }} {% endif %}",
    "body_template": "CPU Queue Length threshold is {{ tstate }}",
    "symptoms": "",
    "probable_causes": "",
    "recommended_actions": ""
}
